{"ticker":"HPQ","name":"HP Inc. Common Stock","sector":"Technology","detailSector":"Computer Hardware","exchange":"NYSE","rows":[{"date":"2026-06-01","ticker":"HPQ","name":"HP Inc. Common Stock","sector":"Technology","detailSector":"Computer Hardware","theme":"Computer Hardware","exchange":"NYSE","close":"$28.99 / 43,807원","closeRaw":28.9871,"currency":"USD","usdKrw":1511.27,"closeKrw":43807.3351831543,"upScore":75.8,"upProb":0.7188624508336138,"upGrade":"YELLOW","downRisk":39.2,"downProb":0.0255476293476073,"downGrade":"GREEN","isUpCandidate":false,"isDownRed":false,"isFinalCandidate":false,"expRet_1m":"-1.8%","expClose_1m":"$28.45","expCloseKrw_1m":"42,997원","expRet_3m":"2.0%","expClose_3m":"$29.58","expCloseKrw_3m":"44,700원","expRet_6m":"26.1%","expClose_6m":"$36.55","expCloseKrw_6m":"55,230원","expRet_12m":"32.8%","expClose_12m":"$38.51","expCloseKrw_12m":"58,192원","growth_profit":70.0,"cash_quality":61.0,"valuation":28.0,"price_volume":17.0,"risk_overheat":50.0},{"date":"2026-06-02","ticker":"HPQ","name":"HP Inc. Common Stock","sector":"Technology","detailSector":"Computer Hardware","theme":"Computer Hardware","exchange":"NYSE","close":"$26.96 / 40,890원","closeRaw":26.9617,"currency":"USD","usdKrw":1516.6,"closeKrw":40890.113561755374,"upScore":61.9,"upProb":0.5865056169362651,"upGrade":"GREEN","downRisk":36.4,"downProb":0.0218524570018117,"downGrade":"GREEN","isUpCandidate":false,"isDownRed":false,"isFinalCandidate":false,"expRet_1m":"-1.7%","expClose_1m":"$26.51","expCloseKrw_1m":"40,199원","expRet_3m":"1.7%","expClose_3m":"$27.43","expCloseKrw_3m":"41,600원","expRet_6m":"26.5%","expClose_6m":"$34.11","expCloseKrw_6m":"51,729원","expRet_12m":"29.6%","expClose_12m":"$34.95","expCloseKrw_12m":"53,000원","growth_profit":70.0,"cash_quality":61.0,"valuation":26.0,"price_volume":29.0,"risk_overheat":49.0},{"date":"2026-06-03","ticker":"HPQ","name":"HP Inc. Common Stock","sector":"Technology","detailSector":"Computer Hardware","theme":"Computer Hardware","exchange":"NYSE","close":"$25.73 / 39,365원","closeRaw":25.7268,"currency":"USD","usdKrw":1530.11,"closeKrw":39364.83357114258,"upScore":60.2,"upProb":0.563766626559593,"upGrade":"GREEN","downRisk":35.2,"downProb":0.0204890232777319,"downGrade":"GREEN","isUpCandidate":false,"isDownRed":false,"isFinalCandidate":false,"expRet_1m":"-0.8%","expClose_1m":"$25.53","expCloseKrw_1m":"39,061원","expRet_3m":"1.3%","expClose_3m":"$26.07","expCloseKrw_3m":"39,896원","expRet_6m":"23.6%","expClose_6m":"$31.81","expCloseKrw_6m":"48,669원","expRet_12m":"28.6%","expClose_12m":"$33.08","expCloseKrw_12m":"50,615원","growth_profit":70.0,"cash_quality":61.0,"valuation":25.0,"price_volume":30.0,"risk_overheat":55.0},{"date":"2026-06-04","ticker":"HPQ","name":"HP Inc. Common Stock","sector":"Technology","detailSector":"Computer Hardware","theme":"Computer Hardware","exchange":"NYSE","close":"$25.98 / 39,835원","closeRaw":25.9836,"currency":"USD","usdKrw":1533.0699,"closeKrw":39834.67625639648,"upScore":62.0,"upProb":0.5831788372076968,"upGrade":"GREEN","downRisk":36.6,"downProb":0.0209897717254613,"downGrade":"GREEN","isUpCandidate":false,"isDownRed":false,"isFinalCandidate":false,"expRet_1m":"-0.8%","expClose_1m":"$25.78","expCloseKrw_1m":"39,526원","expRet_3m":"1.2%","expClose_3m":"$26.31","expCloseKrw_3m":"40,330원","expRet_6m":"23.6%","expClose_6m":"$32.12","expCloseKrw_6m":"49,250원","expRet_12m":"30.0%","expClose_12m":"$33.77","expCloseKrw_12m":"51,779원","growth_profit":70.0,"cash_quality":61.0,"valuation":25.0,"price_volume":30.0,"risk_overheat":57.0},{"date":"2026-06-05","ticker":"HPQ","name":"HP Inc. Common Stock","sector":"Technology","detailSector":"Computer Hardware","theme":"Computer Hardware","exchange":"NYSE","close":"$25.27 / 38,744원","closeRaw":25.2723,"currency":"USD","usdKrw":1533.0699,"closeKrw":38744.20360360108,"upScore":63.6,"upProb":0.5957434179181023,"upGrade":"GREEN","downRisk":32.0,"downProb":0.0168731492824891,"downGrade":"GREEN","isUpCandidate":false,"isDownRed":false,"isFinalCandidate":false,"expRet_1m":"-0.8%","expClose_1m":"$25.06","expCloseKrw_1m":"38,425원","expRet_3m":"1.3%","expClose_3m":"$25.61","expCloseKrw_3m":"39,263원","expRet_6m":"22.3%","expClose_6m":"$30.91","expCloseKrw_6m":"47,395원","expRet_12m":"29.7%","expClose_12m":"$32.77","expCloseKrw_12m":"50,236원","growth_profit":70.0,"cash_quality":61.0,"valuation":25.0,"price_volume":29.0,"risk_overheat":53.0},{"date":"2026-06-08","ticker":"HPQ","name":"HP Inc. Common Stock","sector":"Technology","detailSector":"Computer Hardware","theme":"Computer Hardware","exchange":"NYSE","close":"$25.07 / 38,336원","closeRaw":25.0747,"currency":"USD","usdKrw":1528.88,"closeKrw":38336.207458435056,"upScore":63.8,"upProb":0.5901239524401877,"upGrade":"GREEN","downRisk":29.1,"downProb":0.0151941635739517,"downGrade":"GREEN","isUpCandidate":false,"isDownRed":false,"isFinalCandidate":false,"expRet_1m":"-0.1%","expClose_1m":"$25.05","expCloseKrw_1m":"38,293원","expRet_3m":"1.8%","expClose_3m":"$25.53","expCloseKrw_3m":"39,029원","expRet_6m":"23.5%","expClose_6m":"$30.97","expCloseKrw_6m":"47,342원","expRet_12m":"29.6%","expClose_12m":"$32.50","expCloseKrw_12m":"49,683원","growth_profit":70.0,"cash_quality":61.0,"valuation":25.0,"price_volume":31.0,"risk_overheat":47.0},{"date":"2026-06-09","ticker":"HPQ","name":"HP Inc. Common Stock","sector":"Technology","detailSector":"Computer Hardware","theme":"Computer Hardware","exchange":"NYSE","close":"$24.64 / 37,596원","closeRaw":24.64,"currency":"USD","usdKrw":1525.8101,"closeKrw":37595.95984375,"upScore":59.1,"upProb":0.5320400172937947,"upGrade":"GREEN","downRisk":32.4,"downProb":0.0178439949112553,"downGrade":"GREEN","isUpCandidate":false,"isDownRed":false,"isFinalCandidate":false,"expRet_1m":"-0.1%","expClose_1m":"$24.63","expCloseKrw_1m":"37,573원","expRet_3m":"1.8%","expClose_3m":"$25.09","expCloseKrw_3m":"38,285원","expRet_6m":"22.2%","expClose_6m":"$30.10","expCloseKrw_6m":"45,933원","expRet_12m":"29.9%","expClose_12m":"$32.02","expCloseKrw_12m":"48,849원","growth_profit":70.0,"cash_quality":61.0,"valuation":24.0,"price_volume":32.0,"risk_overheat":50.0},{"date":"2026-06-10","ticker":"HPQ","name":"HP Inc. Common Stock","sector":"Technology","detailSector":"Computer Hardware","theme":"Computer Hardware","exchange":"NYSE","close":"$24.69 / 37,653원","closeRaw":24.69,"currency":"USD","usdKrw":1525.05,"closeKrw":37653.48570556641,"upScore":60.7,"upProb":0.5476808912925577,"upGrade":"GREEN","downRisk":32.4,"downProb":0.0185082772369252,"downGrade":"GREEN","isUpCandidate":false,"isDownRed":false,"isFinalCandidate":false,"expRet_1m":"-0.7%","expClose_1m":"$24.53","expCloseKrw_1m":"37,408원","expRet_3m":"1.8%","expClose_3m":"$25.14","expCloseKrw_3m":"38,344원","expRet_6m":"22.2%","expClose_6m":"$30.17","expCloseKrw_6m":"46,004원","expRet_12m":"30.7%","expClose_12m":"$32.27","expCloseKrw_12m":"49,209원","growth_profit":70.0,"cash_quality":61.0,"valuation":24.0,"price_volume":30.0,"risk_overheat":56.0},{"date":"2026-06-11","ticker":"HPQ","name":"HP Inc. Common Stock","sector":"Technology","detailSector":"Computer Hardware","theme":"Computer Hardware","exchange":"NYSE","close":"$24.68 / 37,449원","closeRaw":24.68,"currency":"USD","usdKrw":1517.38,"closeKrw":37448.93852050781,"upScore":58.6,"upProb":0.5356076832813603,"upGrade":"GREEN","downRisk":32.7,"downProb":0.0182235686349034,"downGrade":"GREEN","isUpCandidate":false,"isDownRed":false,"isFinalCandidate":false,"expRet_1m":"-0.1%","expClose_1m":"$24.65","expCloseKrw_1m":"37,404원","expRet_3m":"1.8%","expClose_3m":"$25.14","expCloseKrw_3m":"38,140원","expRet_6m":"21.9%","expClose_6m":"$30.09","expCloseKrw_6m":"45,665원","expRet_12m":"29.3%","expClose_12m":"$31.91","expCloseKrw_12m":"48,416원","growth_profit":70.0,"cash_quality":61.0,"valuation":23.0,"price_volume":32.0,"risk_overheat":57.0},{"date":"2026-06-12","ticker":"HPQ","name":"HP Inc. Common Stock","sector":"Technology","detailSector":"Computer Hardware","theme":"Computer Hardware","exchange":"NYSE","close":"$25.24 / 38,299원","closeRaw":25.24,"currency":"USD","usdKrw":1517.38,"closeKrw":38298.67132324218,"upScore":63.0,"upProb":0.5876487925702646,"upGrade":"GREEN","downRisk":33.4,"downProb":0.0181642796856913,"downGrade":"GREEN","isUpCandidate":false,"isDownRed":false,"isFinalCandidate":false,"expRet_1m":"0.7%","expClose_1m":"$25.43","expCloseKrw_1m":"38,579원","expRet_3m":"2.4%","expClose_3m":"$25.84","expCloseKrw_3m":"39,202원","expRet_6m":"22.3%","expClose_6m":"$30.86","expCloseKrw_6m":"46,827원","expRet_12m":"29.9%","expClose_12m":"$32.79","expCloseKrw_12m":"49,762원","growth_profit":70.0,"cash_quality":61.0,"valuation":24.0,"price_volume":29.0,"risk_overheat":48.0},{"date":"2026-06-15","ticker":"HPQ","name":"HP Inc. Common Stock","sector":"Technology","detailSector":"Computer Hardware","theme":"Computer Hardware","exchange":"NYSE","close":"$24.60 / 37,227원","closeRaw":24.6,"currency":"USD","usdKrw":1513.3101,"closeKrw":37227.42744140625,"upScore":58.5,"upProb":0.534685836076477,"upGrade":"GREEN","downRisk":35.2,"downProb":0.0204928714635622,"downGrade":"GREEN","isUpCandidate":false,"isDownRed":false,"isFinalCandidate":false,"expRet_1m":"0.3%","expClose_1m":"$24.68","expCloseKrw_1m":"37,350원","expRet_3m":"2.1%","expClose_3m":"$25.12","expCloseKrw_3m":"38,010원","expRet_6m":"21.4%","expClose_6m":"$29.86","expCloseKrw_6m":"45,185원","expRet_12m":"29.9%","expClose_12m":"$31.96","expCloseKrw_12m":"48,370원","growth_profit":70.0,"cash_quality":61.0,"valuation":23.0,"price_volume":31.0,"risk_overheat":52.0},{"date":"2026-06-16","ticker":"HPQ","name":"HP Inc. Common Stock","sector":"Technology","detailSector":"Computer Hardware","theme":"Computer Hardware","exchange":"NYSE","close":"$24.29 / 36,701원","closeRaw":24.29,"currency":"USD","usdKrw":1510.96,"closeKrw":36701.21745117188,"upScore":53.6,"upProb":0.4611595686010905,"upGrade":"GREEN","downRisk":34.6,"downProb":0.018121937326243,"downGrade":"GREEN","isUpCandidate":false,"isDownRed":false,"isFinalCandidate":false,"expRet_1m":"1.1%","expClose_1m":"$24.56","expCloseKrw_1m":"37,103원","expRet_3m":"2.4%","expClose_3m":"$24.87","expCloseKrw_3m":"37,574원","expRet_6m":"20.8%","expClose_6m":"$29.35","expCloseKrw_6m":"44,351원","expRet_12m":"28.0%","expClose_12m":"$31.09","expCloseKrw_12m":"46,970원","growth_profit":70.0,"cash_quality":61.0,"valuation":23.0,"price_volume":31.0,"risk_overheat":48.0},{"date":"2026-06-17","ticker":"HPQ","name":"HP Inc. Common Stock","sector":"Technology","detailSector":"Computer Hardware","theme":"Computer Hardware","exchange":"NYSE","close":"$23.18 / 35,359원","closeRaw":23.18,"currency":"USD","usdKrw":1525.42,"closeKrw":35359.23661865234,"upScore":56.2,"upProb":0.491202408090069,"upGrade":"GREEN","downRisk":34.3,"downProb":0.0205608373834077,"downGrade":"GREEN","isUpCandidate":false,"isDownRed":false,"isFinalCandidate":false,"expRet_1m":"1.2%","expClose_1m":"$23.46","expCloseKrw_1m":"35,780원","expRet_3m":"2.3%","expClose_3m":"$23.70","expCloseKrw_3m":"36,158원","expRet_6m":"20.9%","expClose_6m":"$28.03","expCloseKrw_6m":"42,755원","expRet_12m":"28.2%","expClose_12m":"$29.71","expCloseKrw_12m":"45,325원","growth_profit":70.0,"cash_quality":61.0,"valuation":21.0,"price_volume":34.0,"risk_overheat":45.0},{"date":"2026-06-18","ticker":"HPQ","name":"HP Inc. Common Stock","sector":"Technology","detailSector":"Computer Hardware","theme":"Computer Hardware","exchange":"NYSE","close":"$23.50 / 36,133원","closeRaw":23.5,"currency":"USD","usdKrw":1537.5601,"closeKrw":36132.661376953125,"upScore":56.3,"upProb":0.4855299942037323,"upGrade":"GREEN","downRisk":34.0,"downProb":0.0210520438989389,"downGrade":"GREEN","isUpCandidate":false,"isDownRed":false,"isFinalCandidate":false,"expRet_1m":"1.2%","expClose_1m":"$23.77","expCloseKrw_1m":"36,550원","expRet_3m":"2.5%","expClose_3m":"$24.09","expCloseKrw_3m":"37,043원","expRet_6m":"21.1%","expClose_6m":"$28.47","expCloseKrw_6m":"43,769원","expRet_12m":"28.5%","expClose_12m":"$30.19","expCloseKrw_12m":"46,420원","growth_profit":70.0,"cash_quality":61.0,"valuation":22.0,"price_volume":34.0,"risk_overheat":52.0},{"date":"2026-06-22","ticker":"HPQ","name":"HP Inc. Common Stock","sector":"Technology","detailSector":"Computer Hardware","theme":"Computer Hardware","exchange":"NYSE","close":"$23.54 / 36,229원","closeRaw":23.54,"currency":"USD","usdKrw":1539.05,"closeKrw":36229.23814941407,"upScore":53.8,"upProb":0.4535377768073838,"upGrade":"GREEN","downRisk":29.1,"downProb":0.0165303621369546,"downGrade":"GREEN","isUpCandidate":false,"isDownRed":false,"isFinalCandidate":false,"expRet_1m":"0.9%","expClose_1m":"$23.76","expCloseKrw_1m":"36,573원","expRet_3m":"2.2%","expClose_3m":"$24.07","expCloseKrw_3m":"37,038원","expRet_6m":"21.1%","expClose_6m":"$28.51","expCloseKrw_6m":"43,886원","expRet_12m":"28.5%","expClose_12m":"$30.24","expCloseKrw_12m":"46,544원","growth_profit":70.0,"cash_quality":61.0,"valuation":22.0,"price_volume":35.0,"risk_overheat":58.0},{"date":"2026-06-23","ticker":"HPQ","name":"HP Inc. Common Stock","sector":"Technology","detailSector":"Computer Hardware","theme":"Computer Hardware","exchange":"NYSE","close":"$23.67 / 36,339원","closeRaw":23.67,"currency":"USD","usdKrw":1535.25,"closeKrw":36339.3675,"upScore":55.8,"upProb":0.4683931861463858,"upGrade":"GREEN","downRisk":28.4,"downProb":0.0183746325103299,"downGrade":"GREEN","isUpCandidate":false,"isDownRed":false,"isFinalCandidate":false,"expRet_1m":"-0.7%","expClose_1m":"$23.50","expCloseKrw_1m":"36,078원","expRet_3m":"2.6%","expClose_3m":"$24.29","expCloseKrw_3m":"37,285원","expRet_6m":"19.9%","expClose_6m":"$28.37","expCloseKrw_6m":"43,560원","expRet_12m":"30.2%","expClose_12m":"$30.81","expCloseKrw_12m":"47,305원","growth_profit":70.0,"cash_quality":61.0,"valuation":22.0,"price_volume":45.0,"risk_overheat":41.0},{"date":"2026-06-24","ticker":"HPQ","name":"HP Inc. Common Stock","sector":"Technology","detailSector":"Computer Hardware","theme":"Computer Hardware","exchange":"NYSE","close":"$23.29 / 35,931원","closeRaw":23.29,"currency":"USD","usdKrw":1542.76,"closeKrw":35930.8806274414,"upScore":60.6,"upProb":0.5340400486935376,"upGrade":"GREEN","downRisk":28.0,"downProb":0.0185011785555328,"downGrade":"GREEN","isUpCandidate":false,"isDownRed":false,"isFinalCandidate":false,"expRet_1m":"-0.6%","expClose_1m":"$23.15","expCloseKrw_1m":"35,708원","expRet_3m":"2.5%","expClose_3m":"$23.87","expCloseKrw_3m":"36,821원","expRet_6m":"20.1%","expClose_6m":"$27.98","expCloseKrw_6m":"43,166원","expRet_12m":"29.9%","expClose_12m":"$30.26","expCloseKrw_12m":"46,681원","growth_profit":70.0,"cash_quality":61.0,"valuation":21.0,"price_volume":49.0,"risk_overheat":38.0},{"date":"2026-06-25","ticker":"HPQ","name":"HP Inc. Common Stock","sector":"Technology","detailSector":"Computer Hardware","theme":"Computer Hardware","exchange":"NYSE","close":"$22.92 / 35,445원","closeRaw":22.92,"currency":"USD","usdKrw":1546.48,"closeKrw":35445.32115234375,"upScore":58.6,"upProb":0.5091974545890565,"upGrade":"GREEN","downRisk":28.4,"downProb":0.018576117903621,"downGrade":"GREEN","isUpCandidate":false,"isDownRed":false,"isFinalCandidate":false,"expRet_1m":"-0.1%","expClose_1m":"$22.89","expCloseKrw_1m":"35,405원","expRet_3m":"1.4%","expClose_3m":"$23.25","expCloseKrw_3m":"35,951원","expRet_6m":"20.5%","expClose_6m":"$27.63","expCloseKrw_6m":"42,726원","expRet_12m":"29.9%","expClose_12m":"$29.78","expCloseKrw_12m":"46,050원","growth_profit":70.0,"cash_quality":61.0,"valuation":20.0,"price_volume":53.0,"risk_overheat":39.0},{"date":"2026-06-26","ticker":"HPQ","name":"HP Inc. Common Stock","sector":"Technology","detailSector":"Computer Hardware","theme":"Computer Hardware","exchange":"NYSE","close":"$22.88 / 35,383원","closeRaw":22.88,"currency":"USD","usdKrw":1546.48,"closeKrw":35383.461953125,"upScore":57.8,"upProb":0.504924772453777,"upGrade":"GREEN","downRisk":29.5,"downProb":0.0197162784019391,"downGrade":"GREEN","isUpCandidate":false,"isDownRed":false,"isFinalCandidate":false,"expRet_1m":"0.5%","expClose_1m":"$22.99","expCloseKrw_1m":"35,547원","expRet_3m":"1.4%","expClose_3m":"$23.21","expCloseKrw_3m":"35,888원","expRet_6m":"19.5%","expClose_6m":"$27.34","expCloseKrw_6m":"42,279원","expRet_12m":"29.9%","expClose_12m":"$29.73","expCloseKrw_12m":"45,975원","growth_profit":70.0,"cash_quality":61.0,"valuation":20.0,"price_volume":56.0,"risk_overheat":42.0},{"date":"2026-06-29","ticker":"HPQ","name":"HP Inc. Common Stock","sector":"Technology","detailSector":"Computer Hardware","theme":"Computer Hardware","exchange":"NYSE","close":"$22.64 / 34,905원","closeRaw":22.64,"currency":"USD","usdKrw":1541.73,"closeKrw":34904.766757812504,"upScore":59.4,"upProb":0.5377254556126485,"upGrade":"GREEN","downRisk":30.9,"downProb":0.0183471017717262,"downGrade":"GREEN","isUpCandidate":false,"isDownRed":false,"isFinalCandidate":false,"expRet_1m":"0.6%","expClose_1m":"$22.77","expCloseKrw_1m":"35,112원","expRet_3m":"1.3%","expClose_3m":"$22.93","expCloseKrw_3m":"35,355원","expRet_6m":"20.1%","expClose_6m":"$27.19","expCloseKrw_6m":"41,914원","expRet_12m":"31.0%","expClose_12m":"$29.66","expCloseKrw_12m":"45,729원","growth_profit":70.0,"cash_quality":61.0,"valuation":19.0,"price_volume":61.0,"risk_overheat":34.0},{"date":"2026-06-30","ticker":"HPQ","name":"HP Inc. Common Stock","sector":"Technology","detailSector":"Computer Hardware","theme":"Computer Hardware","exchange":"NYSE","close":"$21.94 / 33,977원","closeRaw":21.94,"currency":"USD","usdKrw":1548.61,"closeKrw":33976.503078613285,"upScore":64.7,"upProb":0.5914763427160671,"upGrade":"GREEN","downRisk":35.0,"downProb":0.0230192577359797,"downGrade":"GREEN","isUpCandidate":false,"isDownRed":false,"isFinalCandidate":false,"expRet_1m":"1.5%","expClose_1m":"$22.28","expCloseKrw_1m":"34,499원","expRet_3m":"1.0%","expClose_3m":"$22.16","expCloseKrw_3m":"34,325원","expRet_6m":"17.9%","expClose_6m":"$25.86","expCloseKrw_6m":"40,053원","expRet_12m":"28.5%","expClose_12m":"$28.19","expCloseKrw_12m":"43,661원","growth_profit":70.0,"cash_quality":61.0,"valuation":18.0,"price_volume":67.0,"risk_overheat":28.0},{"date":"2026-07-01","ticker":"HPQ","name":"HP Inc. Common Stock","sector":"Technology","detailSector":"Computer Hardware","theme":"Computer Hardware","exchange":"NYSE","close":"$22.02 / 34,100원","closeRaw":22.02,"currency":"USD","usdKrw":1548.61,"closeKrw":34100.391877441405,"upScore":56.1,"upProb":0.5446796910740895,"upGrade":"GREEN","downRisk":20.8,"downProb":0.0096193014341127,"downGrade":"GREEN","isUpCandidate":false,"isDownRed":false,"isFinalCandidate":false,"expRet_1m":"0.7%","expClose_1m":"$22.17","expCloseKrw_1m":"34,331원","expRet_3m":"3.5%","expClose_3m":"$22.79","expCloseKrw_3m":"35,299원","expRet_6m":"24.2%","expClose_6m":"$27.35","expCloseKrw_6m":"42,359원","expRet_12m":"28.6%","expClose_12m":"$28.32","expCloseKrw_12m":"43,858원","growth_profit":70.0,"cash_quality":61.0,"valuation":17.0,"price_volume":65.0,"risk_overheat":36.0}]}